isla/AdjustComponent.py
isla/AdjustConnector.py
isla/AmberKESS.py
isla/Arctic.py
isla/Biodiesel.py
isla/Biogas.py
isla/Biomass.py
isla/Coal.py
isla/CombBase.py
isla/CombPeak.py
isla/Component.py
isla/Connector.py
isla/Control.py
isla/DesalLoad.py
isla/DesalSink.py
isla/DesalStorage.py
isla/Desalinate.py
isla/Diesel.py
isla/Dispatch.py
isla/DispatchableComponent.py
isla/DispatchableConnector.py
isla/DoubleStorage.py
isla/DoubleStorageConnector.py
isla/EDDesal.py
isla/Ethanol.py
isla/FESEnergy.py
isla/FESLoad.py
isla/FESPower.py
isla/FixedComponent.py
isla/FixedConnector.py
isla/Fuel.py
isla/Gasoline.py
isla/Genset.py
isla/Geothermal.py
isla/Grid.py
isla/GridComponent.py
isla/GridConnector.py
isla/H2Electrolyzer.py
isla/H2FuelCell.py
isla/H2Storage.py
isla/H2WaterLoad.py
isla/HFO.py
isla/HVACLoad.py
isla/Hydro.py
isla/HydrogenEnergy.py
isla/HydrogenPower.py
isla/IdealStorage.py
isla/IntermittentComponent.py
isla/IntermittentConnector.py
isla/LiIon.py
isla/Load.py
isla/LoadComponent.py
isla/LoadConnector.py
isla/LoadFollow.py
isla/MEDDesal.py
isla/MSFDesal.py
isla/MVCDesal.py
isla/Methanol.py
isla/NaS.py
isla/NatGas.py
isla/NullComp.py
isla/Partial37Storage.py
isla/Partial37StorageConnector.py
isla/PbAcid.py
isla/PropGas.py
isla/PropLiq.py
isla/PumpedHydro.py
isla/RODesal.py
isla/RORHydro.py
isla/SinkComponent.py
isla/SinkConnector.py
isla/SolarPV.py
isla/SolarPVDev.py
isla/SolarPVLegacy.py
isla/StorageComponent.py
isla/StorageConnector.py
isla/SupplementaryComponent.py
isla/SupplementaryConnector.py
isla/ThermalLoad.py
isla/VRBEnergy.py
isla/VRBPower.py
isla/Wind.py
isla/__init__.py
isla/hydro_eff.csv
isla/li_ocv.csv
isla/li_rf.csv
isla/na_rintc.csv
isla/na_rintd.csv
isla/pb_ocv.csv
isla/tools.py
isla-1.8.1.dist-info/LICENSE.txt
isla-1.8.1.dist-info/METADATA
isla-1.8.1.dist-info/WHEEL
isla-1.8.1.dist-info/top_level.txt
isla-1.8.1.dist-info/RECORD
