Metadata-Version: 2.1
Name: isla
Version: 1.8.1
Summary: A Python package for energy systems modeling.
Home-page: https://github.com/isla-opt/ISLA
Author: UP Laboratory of Electrochemical Engineering
License: UNKNOWN
Keywords: isla island renewable energy model modelling simulation optimization
Platform: UNKNOWN
Classifier: Development Status :: 2 - Pre-Alpha
Classifier: Intended Audience :: Science/Research
Classifier: Topic :: Software Development :: Build Tools
Classifier: License :: OSI Approved :: MIT License
Classifier: Programming Language :: Python :: 3.8
Requires-Python: ~=3.8
Requires-Dist: numpy
Requires-Dist: scipy
Requires-Dist: pandas
Requires-Dist: matplotlib
